Linked_List_lib/__about__.py
Linked_List_lib/__init__.py
Linked_List_lib/__pycache__/__about__.cpython-38.pyc
Linked_List_lib/__pycache__/__init__.cpython-38.pyc
Linked_List_lib/singly_linked_list/__init__.py
Linked_List_lib/singly_linked_list/sll.py
Linked_List_lib/singly_linked_list/__pycache__/__init__.cpython-38.pyc
Linked_List_lib/singly_linked_list/__pycache__/sll.cpython-38.pyc
Linked_List_lib-0.0.3.dist-info/LICENSE
Linked_List_lib-0.0.3.dist-info/METADATA
Linked_List_lib-0.0.3.dist-info/WHEEL
Linked_List_lib-0.0.3.dist-info/top_level.txt
Linked_List_lib-0.0.3.dist-info/RECORD
