Metadata-Version: 2.1
Name: Linked-List-lib
Version: 0.0.3
Summary: Library for Studying and Applying Linked List Data Structure
Home-page: https://github.com/daniel-yj-yang/Linked_List_lib
Author: Daniel Yang
Author-email: daniel.yj.yang@gmail.com
License: BSD 3-Clause
Platform: UNKNOWN
Classifier: Development Status :: 3 - Alpha
Classifier: Programming Language :: Python :: 3
Classifier: Programming Language :: Python :: 3.8
Classifier: Programming Language :: Python :: 3.9
Classifier: License :: OSI Approved :: BSD License
Classifier: Operating System :: OS Independent
Requires-Python: >=3.8
License-File: LICENSE
